ammolite/__init__.py
ammolite/cgo.py
ammolite/convert.py
ammolite/display.py
ammolite/object.py
ammolite/shapes.py
ammolite/startup.py
ammolite-0.8.0.dist-info/LICENSE
ammolite-0.8.0.dist-info/WHEEL
ammolite-0.8.0.dist-info/METADATA
ammolite-0.8.0.dist-info/RECORD
