Metadata-Version: 2.1
Name: ammolite
Version: 0.8.0
Summary: Visualize structure data from Biotite with PyMOL
Home-page: https://ammolite.biotite-python.org
License: BSD-3-Clause
Keywords: Bioinformatics,Computational biology,Data visualization
Author: Patrick Kunzmann
Author-email: patrick.kunzm@gmail.com
Requires-Python: >=3.7,<4.0
Classifier: Development Status :: 4 - Beta
Classifier: Intended Audience :: Science/Research
Classifier: License :: OSI Approved :: BSD License
Classifier: Natural Language :: English
Classifier: Operating System :: MacOS
Classifier: Operating System :: Microsoft :: Windows
Classifier: Operating System :: POSIX :: Linux
Classifier: Programming Language :: Python :: 3
Classifier: Programming Language :: Python :: 3.10
Classifier: Programming Language :: Python :: 3.7
Classifier: Programming Language :: Python :: 3.8
Classifier: Programming Language :: Python :: 3.9
Classifier: Topic :: Scientific/Engineering :: Bio-Informatics
Requires-Dist: biotite (>=0.28)
Project-URL: Documentation, https://ammolite.biotite-python.org
Project-URL: Repository, https://github.com/biotite-dev/ammolite
